CHANGES.rst
MANIFEST.in
README.md
setup.py
src/wai.tfrecords.egg-info/PKG-INFO
src/wai.tfrecords.egg-info/SOURCES.txt
src/wai.tfrecords.egg-info/dependency_links.txt
src/wai.tfrecords.egg-info/entry_points.txt
src/wai.tfrecords.egg-info/namespace_packages.txt
src/wai.tfrecords.egg-info/requires.txt
src/wai.tfrecords.egg-info/top_level.txt
src/wai/tfrecords/__init__.py
src/wai/tfrecords/adams/_ImageFormat.py
src/wai/tfrecords/adams/__init__.py
src/wai/tfrecords/adams/__main__.py
src/wai/tfrecords/adams/_convert.py
src/wai/tfrecords/adams/_determine_labels.py
src/wai/tfrecords/adams/_fix_labels.py
src/wai/tfrecords/adams/_get_files_from_directory.py
src/wai/tfrecords/adams/_logging.py
src/wai/tfrecords/adams/_main.py
src/wai/tfrecords/adams/_to_tf_example.py
src/wai/tfrecords/adams/_write_protobuf_label_map.py
src/wai/tfrecords/adams/constants.py
src/wai/tfrecords/object_detection/__init__.py
src/wai/tfrecords/object_detection/eval_util.py
src/wai/tfrecords/object_detection/eval_util_test.py
src/wai/tfrecords/object_detection/export_inference_graph.py
src/wai/tfrecords/object_detection/export_tflite_ssd_graph.py
src/wai/tfrecords/object_detection/export_tflite_ssd_graph_lib.py
src/wai/tfrecords/object_detection/export_tflite_ssd_graph_lib_test.py
src/wai/tfrecords/object_detection/exporter.py
src/wai/tfrecords/object_detection/exporter_test.py
src/wai/tfrecords/object_detection/inputs.py
src/wai/tfrecords/object_detection/inputs_test.py
src/wai/tfrecords/object_detection/model_hparams.py
src/wai/tfrecords/object_detection/model_lib.py
src/wai/tfrecords/object_detection/model_lib_test.py
src/wai/tfrecords/object_detection/model_lib_v2.py
src/wai/tfrecords/object_detection/model_lib_v2_test.py
src/wai/tfrecords/object_detection/model_main.py
src/wai/tfrecords/object_detection/model_tpu_main.py
src/wai/tfrecords/object_detection/anchor_generators/__init__.py
src/wai/tfrecords/object_detection/anchor_generators/flexible_grid_anchor_generator.py
src/wai/tfrecords/object_detection/anchor_generators/flexible_grid_anchor_generator_test.py
src/wai/tfrecords/object_detection/anchor_generators/grid_anchor_generator.py
src/wai/tfrecords/object_detection/anchor_generators/grid_anchor_generator_test.py
