Metadata-Version: 1.1
Name: wai.tfrecords
Version: 0.0.2
Summary: Converting ADAMS annotations to tfrecords.
Home-page: https://github.com/waikato-datamining/tensorflow/tfrecords
Author: Peter Reutemann
Author-email: fracpete@waikato.ac.nz
License: MIT License
Platform: UNKNOWN
Classifier: Development Status :: 4 - Beta
Classifier: License :: OSI Approved :: MIT License
Classifier: Topic :: Scientific/Engineering :: Artificial Intelligence
Classifier: Programming Language :: Python :: 3
